tmmpred/__init__.py
tmmpred/__main__.py
tmmpred/tmmpred.py
tmmpred/data/__init__.py
tmmpred/data/fmo_bvmo.hmm
tmmpred-0.2.0.dist-info/METADATA
tmmpred-0.2.0.dist-info/WHEEL
tmmpred-0.2.0.dist-info/entry_points.txt
tmmpred-0.2.0.dist-info/licenses/LICENSE
tmmpred-0.2.0.dist-info/RECORD
