Metadata-Version: 2.3
Name: tmmpred
Version: 0.2.0
Summary: Package for predicting Tmm sequences (FMO subfamily with trimethylamine monooxidase activity).
Project-URL: Homepage, https://gitlab.norceresearch.no/papu/tmmpred
Project-URL: Issues, https://gitlab.norceresearch.no/papu/tmmpred/issues
Author-email: Pål Puntervoll <papu@norceresearch.no>
License-File: LICENSE
Classifier: License :: OSI Approved :: MIT License
Classifier: Operating System :: OS Independent
Classifier: Programming Language :: Python :: 3
Requires-Python: >=3.7
Requires-Dist: pyhmmer>=0.10
